{"user1": {"username": "user1", "password": "password1", "created": "2020-07-07 00:16:28.293901"}, "user2": {"username": "user2", "password": "password2", "created": "2020-07-07 00:28:07.315781"}, "e1": {"username": "e1", "password": "p1", "created": "2021-03-31 22-07-42"}, "gmn": {"username": "gmn", "password": "nmn", "created": "2021-03-31 22-21-00"}, "scsdc": {"username": "scsdc", "password": "vxc", "created": "2021-03-31 22-31-32"}, "yju": {"username": "yju", "password": "uyjku", "created": "2021-03-31 22-33-29"}, "ghg": {"username": "ghg", "password": "", "created": "2021-03-31 22-35-45"}, "d": {"username": "d", "password": "e", "created": "2021-03-31 22-36-41"}, "f": {"username": "f", "password": "f", "created": "2021-03-31 22-37-00"}, "nh": {"username": "nh", "password": "hjh", "created": "2021-03-31 22-39-14"}, "k,k": {"username": "k,k", "password": ",l,,", "created": "2021-03-31 22-42-04"}, "jh": {"username": "jh", "password": "io", "created": "2021-03-31 22-43-08"}, "": {"username": "", "password": "", "created": "2021-04-01 17-30-04"}, "jj": {"username": "jj", "password": "jj", "created": "2021-04-01 12-58-36"}, "dfd\t": {"username": "fd\t", "password": "pass", "created": "2021-04-01 17-20-34"}, "ff": {"username": "ff", "password": "ff", "created": "2021-04-01 18-29-30"}}